elegooMarsUtility/__init__.py
elegooMarsUtility/emUtility.py
elegooMarsUtility/main.py
elegooMarsUtility/xyCompensateGui.py
ElegooMarsUtility-0.2.1.dist-info/LICENCE
ElegooMarsUtility-0.2.1.dist-info/METADATA
ElegooMarsUtility-0.2.1.dist-info/WHEEL
ElegooMarsUtility-0.2.1.dist-info/entry_points.txt
ElegooMarsUtility-0.2.1.dist-info/top_level.txt
ElegooMarsUtility-0.2.1.dist-info/RECORD
