Metadata-Version: 2.1
Name: ElegooMarsUtility
Version: 0.2.1
Summary: Utility to post process sliced models for Elegoo Mars
Home-page: https://github.com/yaqwsx/ElegooMarsUtility
Author: Jan Mrázek
Author-email: email@honzamrazek.cz
License: UNKNOWN
Platform: UNKNOWN
Classifier: Programming Language :: Python :: 3
Classifier: License :: OSI Approved :: MIT License
Classifier: Operating System :: OS Independent
Requires-Dist: click
Requires-Dist: numpy
Requires-Dist: pyphotonfile (>=0.2)
Requires-Dist: scikit-image
Requires-Dist: Pillow (==6.2.0)
